README.md
setup.py
DS_OOP_Review.egg-info/PKG-INFO
DS_OOP_Review.egg-info/SOURCES.txt
DS_OOP_Review.egg-info/dependency_links.txt
DS_OOP_Review.egg-info/requires.txt
DS_OOP_Review.egg-info/top_level.txt
Weather/__init__.py
Weather/weather_test.py
football/__init__.py
football/football_test.py
football/game.py
football/players.py
football/possible_values.py
football/season.py