Metadata-Version: 2.1
Name: DS-OOP-Review
Version: 0.1.2
Summary: two modules
Home-page: https://github.com/Zebfred/DS-OOP-Review
Author: Zebfred
License: UNKNOWN
Platform: UNKNOWN
Classifier: Programming Language :: Python :: 3
Classifier: License :: OSI Approved :: MIT License
Classifier: Operating System :: OS Independent
Requires-Python: >=3.5
